taskcheck/__main__.py
taskcheck/common.py
taskcheck/ical.py
taskcheck/install.py
taskcheck/parallel.py
taskcheck/report.py
taskcheck-1.0.0.post3.dist-info/METADATA
taskcheck-1.0.0.post3.dist-info/WHEEL
taskcheck-1.0.0.post3.dist-info/entry_points.txt
taskcheck-1.0.0.post3.dist-info/top_level.txt
taskcheck-1.0.0.post3.dist-info/RECORD
