Metadata-Version: 2.4
Name: taskcheck
Version: 1.0.0.post3
Summary: Automatic scheduler for taskwarrior
Requires-Python: >=3.11
Requires-Dist: appdirs>=1.4.4
Requires-Dist: icalendar>=6.0.1
Requires-Dist: random-unicode-emoji>=2.8
Requires-Dist: requests>=2.32.3
Requires-Dist: rich>=13.9.4
